<NotepadPlus>
    <Session activeView="0">
        <mainView activeIndex="3">
            <File firstVisibleLine="0" xOffset="0" scrollWidth="888" startPos="920" endPos="920" selMode="0" lang="Normal Text" encoding="-1" filename="C:\Sandbox\Moonward\DCEngine\DCEngine\Projects\Rebound\Resources\MusicBackground.Zilch" backupFilePath="" originalFileLastModifTimestamp="1460251847" />
            <File firstVisibleLine="112" xOffset="0" scrollWidth="1160" startPos="3076" endPos="3124" selMode="0" lang="Normal Text" encoding="-1" filename="C:\Sandbox\Moonward\DCEngine\DCEngine\Projects\Rebound\Resources\UIButton.Zilch" backupFilePath="" originalFileLastModifTimestamp="1460252399" />
            <File firstVisibleLine="0" xOffset="0" scrollWidth="736" startPos="664" endPos="617" selMode="0" lang="Normal Text" encoding="-1" filename="C:\Sandbox\Moonward\DCEngine\DCEngine\Projects\Rebound\Resources\AntiEnergyField.Zilch" backupFilePath="" originalFileLastModifTimestamp="1460258980" />
            <File firstVisibleLine="0" xOffset="0" scrollWidth="720" startPos="503" endPos="503" selMode="0" lang="Normal Text" encoding="-1" filename="C:\Sandbox\Moonward\DCEngine\DCEngine\Projects\Rebound\Resources\PressurePlate.Zilch" backupFilePath="" originalFileLastModifTimestamp="1460258964" />
            <File firstVisibleLine="0" xOffset="0" scrollWidth="768" startPos="812" endPos="812" selMode="0" lang="Normal Text" encoding="-1" filename="C:\Sandbox\Moonward\DCEngine\DCEngine\Projects\Rebound\Resources\EnergyShield.Zilch" backupFilePath="" originalFileLastModifTimestamp="1460259479" />
            <File firstVisibleLine="3" xOffset="0" scrollWidth="1216" startPos="894" endPos="894" selMode="0" lang="Normal Text" encoding="-1" filename="C:\Sandbox\Moonward\DCEngine\DCEngine\Projects\Rebound\Resources\PlayerController.Zilch" backupFilePath="" originalFileLastModifTimestamp="1460259430" />
        </mainView>
        <subView activeIndex="0" />
    </Session>
</NotepadPlus>
